{
  "ActiveParkings": {
    "1234": {
      "Id": 1234,
      "StartTime": "2024-12-02T09:00:00",
      "EndTime": null,
      "Location": "Stockholm",
      "Cost": 0
    }
  },
  "ParkingHistory": [
    {
      "Id": 5678,
      "StartTime": "2024-12-01T10:00:00",
      "EndTime": "2024-12-01T12:00:00",
      "Location": "G\u00F6teborg",
      "Cost": 40.0
    },
    {
      "Id": 9874,
      "StartTime": "2024-12-03T10:10:13.5758643+01:00",
      "EndTime": "2024-12-03T10:10:43.817644+01:00",
      "Location": "Malm\u00F6",
      "Cost": 0.16800988722222220
    },
    {
      "Id": 5296,
      "StartTime": "2024-12-03T10:12:15.0037224+01:00",
      "EndTime": "2024-12-03T10:13:00.8953638+01:00",
      "Location": "Askim",
      "Cost": 0.2549535633333340
    }
  ]
}